pachinko_SDLR_DV/Pachinko.py
pachinko_SDLR_DV/__init__.py
pachinko_sdlr_dv-0.1.6.dist-info/licenses/LICENSE
pachinko_sdlr_dv-0.1.6.dist-info/METADATA
pachinko_sdlr_dv-0.1.6.dist-info/WHEEL
pachinko_sdlr_dv-0.1.6.dist-info/top_level.txt
pachinko_sdlr_dv-0.1.6.dist-info/RECORD
