Metadata-Version: 2.4
Name: pachinko-sdlr-dv
Version: 0.1.6
Summary: Simulador de Pachinko con modo fiebre y números aleatorios.
Author: Daniel Vega, Sergio de la Rubia
License: MIT
Requires-Python: >=3.8
License-File: LICENSE
Dynamic: license-file
